<?xml version="1.0" ?>
<ExportAPERO>
     <OrientationConique>
          <OrIntImaM2C>
               <I00>0 0</I00>
               <V10>1 0</V10>
               <V01>0 1</V01>
          </OrIntImaM2C>
          <TypeProj>eProjStenope</TypeProj>
          <ZoneUtileInPixel>true</ZoneUtileInPixel>
          <FileInterne>ori/AutoCal_Foc-24000_Cam-DSLRA850.xml</FileInterne>
          <RelativeNameFI>true</RelativeNameFI>
          <Externe>
               <AltiSol>-9.33642612560349683</AltiSol>
               <Profondeur>12.3588065456549554</Profondeur>
               <Time>-1.00000000000000002e+30</Time>
               <KnownConv>eConvApero_DistM2C</KnownConv>
               <Centre>13.1863456411504334 0.599733494804383094 1.38020645763659289</Centre>
               <IncCentre>1 1 1</IncCentre>
               <ParamRotation>
                    <CodageMatr>
                         <L1>0.954973888364376577 -0.0751196255492004722 -0.28702249807213942</L1>
                         <L2>-0.137358654389717061 -0.969434666433027781 -0.203295419481430067</L2>
                         <L3>-0.262978083890026137 0.233566841343612525 -0.93610312360246839</L3>
                    </CodageMatr>
               </ParamRotation>
          </Externe>
          <Verif>
               <Tol>0.00100000000000000002</Tol>
               <ShowMes>true</ShowMes>
               <Appuis>
                    <Num>0</Num>
                    <Im>4412.9431514738817 2891.62919998159987</Im>
                    <Ter>13.357903140732299 -2.92492871347418415 -6.0274856654554112</Ter>
               </Appuis>
               <Appuis>
                    <Num>1</Num>
                    <Im>1765.44207572949881 2836.48064804068599</Im>
                    <Ter>7.94343453557060197 -2.60718462762928027 -5.7807156036007985</Ter>
               </Appuis>
               <Appuis>
                    <Num>2</Num>
                    <Im>1177.07301521301724 3412.04538345337414</Im>
                    <Ter>0.510457266783875596 -7.59750672037078623 -11.1922453096775492</Ter>
               </Appuis>
               <Appuis>
                    <Num>3</Num>
                    <Im>3940.18648338313142 3784.92572021463138</Im>
                    <Ter>12.0780102693577405 -6.49134808144869258 -8.2112867563798364</Ter>
               </Appuis>
               <Appuis>
                    <Num>4</Num>
                    <Im>1965.56604194661281 3275.95986556983553</Im>
                    <Ter>6.38783522035705253 -5.20382174890604254 -8.39058696184468644</Ter>
               </Appuis>
               <Appuis>
                    <Num>5</Num>
                    <Im>5125.39645385741915 272.612965106966101</Im>
                    <Ter>16.9578116715926512 2.69185600594128438 -17.007716853207139</Ter>
               </Appuis>
               <Appuis>
                    <Num>6</Num>
                    <Im>5466.23653793333324 3567.01186752318381</Im>
                    <Ter>17.5298958961793119 -10.4888514941027076 -15.431217788685327</Ter>
               </Appuis>
               <Appuis>
                    <Num>7</Num>
                    <Im>2933.59893894195602 2080.66858291625977</Im>
                    <Ter>9.72056247385721939 -1.91851875669713201 -9.10047230953677477</Ter>
               </Appuis>
               <Appuis>
                    <Num>8</Num>
                    <Im>2571.64231681829324 187.127906084297337</Im>
                    <Ter>9.31317978666345425 3.18082550621217042 -9.61745395533888825</Ter>
               </Appuis>
               <Appuis>
                    <Num>9</Num>
                    <Im>1042.52594375615718 2999.83042144772389</Im>
                    <Ter>-0.161018222314270432 -5.97904864064717056 -11.7163235453412558</Ter>
               </Appuis>
          </Verif>
          <ConvOri>
               <KnownConv>eConvApero_DistM2C</KnownConv>
          </ConvOri>
     </OrientationConique>
</ExportAPERO>
