<?xml version="1.0" ?>
<ExportAPERO>
     <OrientationConique>
          <OrIntImaM2C>
               <I00>0 0</I00>
               <V10>1 0</V10>
               <V01>0 1</V01>
          </OrIntImaM2C>
          <TypeProj>eProjStenope</TypeProj>
          <ZoneUtileInPixel>true</ZoneUtileInPixel>
          <FileInterne>ori/AutoCal_Foc-24000_Cam-DSLRA850.xml</FileInterne>
          <RelativeNameFI>true</RelativeNameFI>
          <Externe>
               <AltiSol>-13.0564186275068135</AltiSol>
               <Profondeur>14.3206173263029051</Profondeur>
               <Time>-1.00000000000000002e+30</Time>
               <KnownConv>eConvApero_DistM2C</KnownConv>
               <Centre>21.2580208900205321 -1.44387891578961058 -3.38809549272815236</Centre>
               <IncCentre>1 1 1</IncCentre>
               <ParamRotation>
                    <CodageMatr>
                         <L1>0.430438347575238633 -0.0841307476205672838 -0.898690628771382283</L1>
                         <L2>-0.358117213405991563 -0.929847141091498242 -0.0844769534624380813</L2>
                         <L3>-0.828537802637287935 0.358198703946248087 -0.430370535808624555</L3>
                    </CodageMatr>
               </ParamRotation>
          </Externe>
          <Verif>
               <Tol>0.00100000000000000002</Tol>
               <ShowMes>true</ShowMes>
               <Appuis>
                    <Num>0</Num>
                    <Im>3913.17216682433809 2497.3310165405278</Im>
                    <Ter>14.4499816402375814 -3.76281509332046138 -8.12777757131800449</Ter>
               </Appuis>
               <Appuis>
                    <Num>1</Num>
                    <Im>4836.32329559308255 2468.81442260736003</Im>
                    <Ter>13.271383621337332 -5.37924501336962102 -11.8265448008693213</Ter>
               </Appuis>
               <Appuis>
                    <Num>2</Num>
                    <Im>189.398835897493797 592.14283847811339</Im>
                    <Ter>8.61542497132806773 3.77971113697228001 -3.15854915897133637</Ter>
               </Appuis>
               <Appuis>
                    <Num>3</Num>
                    <Im>5781.98947906493413 2405.93170166015716</Im>
                    <Ter>12.1567059675213596 -7.71580263273924416 -17.5583013080785619</Ter>
               </Appuis>
               <Appuis>
                    <Num>4</Num>
                    <Im>5626.08271980461723 2059.16710281374162</Im>
                    <Ter>12.6422226581224511 -6.0068229208823567 -16.5769683473060674</Ter>
               </Appuis>
               <Appuis>
                    <Num>5</Num>
                    <Im>2736.79543590555841 3959.57153320279849</Im>
                    <Ter>4.41278686549673793 -10.2947471084023832 -6.90641147742670825</Ter>
               </Appuis>
               <Appuis>
                    <Num>6</Num>
                    <Im>1502.0536608697264 1807.55402755738533</Im>
                    <Ter>0.0652147269038856336 0.319598997705031529 -6.24951110873299065</Ter>
               </Appuis>
               <Appuis>
                    <Num>7</Num>
                    <Im>4491.62309646601989 473.486357688948658</Im>
                    <Ter>6.49282004382290268 1.25164079625934521 -21.2950240909353248</Ter>
               </Appuis>
               <Appuis>
                    <Num>8</Num>
                    <Im>2206.93228054046631 1477.83875083923385</Im>
                    <Ter>13.6487732763483915 -0.662023159658554294 -5.84360647152276869</Ter>
               </Appuis>
               <Appuis>
                    <Num>9</Num>
                    <Im>1053.95920944214345 666.190501213064294</Im>
                    <Ter>2.56532610886781853 5.28959647043103054 -5.97834775926781692</Ter>
               </Appuis>
          </Verif>
          <ConvOri>
               <KnownConv>eConvApero_DistM2C</KnownConv>
          </ConvOri>
     </OrientationConique>
</ExportAPERO>
