<?xml version="1.0" ?>
<ExportAPERO>
     <OrientationConique>
          <OrIntImaM2C>
               <I00>0 0</I00>
               <V10>1 0</V10>
               <V01>0 1</V01>
          </OrIntImaM2C>
          <TypeProj>eProjStenope</TypeProj>
          <ZoneUtileInPixel>true</ZoneUtileInPixel>
          <FileInterne>ori/AutoCal_Foc-24000_Cam-DSLRA850.xml</FileInterne>
          <RelativeNameFI>true</RelativeNameFI>
          <Externe>
               <AltiSol>-9.1923306701677916</AltiSol>
               <Profondeur>9.1634146535236134</Profondeur>
               <Time>-1.00000000000000002e+30</Time>
               <KnownConv>eConvApero_DistM2C</KnownConv>
               <Centre>-1.98990364669105846 -0.0881305411489201052 -0.0832043921250169433</Centre>
               <IncCentre>1 1 1</IncCentre>
               <ParamRotation>
                    <CodageMatr>
                         <L1>0.999564189864667996 0.00460153217935568761 -0.0291591536535673497</L1>
                         <L2>-0.00515645641383627451 -0.945373540197522955 -0.325948278798423363</L2>
                         <L3>-0.0290661538123330454 0.325956585139807964 -0.944937809226910397</L3>
                    </CodageMatr>
               </ParamRotation>
          </Externe>
          <Verif>
               <Tol>0.00100000000000000002</Tol>
               <ShowMes>true</ShowMes>
               <Appuis>
                    <Num>0</Num>
                    <Im>5977.34129333491819 3271.0423164367503</Im>
                    <Ter>7.02714260197842044 -8.17261566932064554 -11.1988426603548401</Ter>
               </Appuis>
               <Appuis>
                    <Num>1</Num>
                    <Im>1049.76690387725989 3246.69489669800078</Im>
                    <Ter>-6.41876255720176125 -5.45114102571616232 -7.32045691484740324</Ter>
               </Appuis>
               <Appuis>
                    <Num>2</Num>
                    <Im>4795.63707733139745 2837.54096603384005</Im>
                    <Ter>1.18300870743272046 -4.17216671877532441 -7.01325412098433976</Ter>
               </Appuis>
               <Appuis>
                    <Num>3</Num>
                    <Im>4693.57726478574295 621.631010055560068</Im>
                    <Ter>1.58089475293489778 -0.203750602307128825 -10.075901742325355</Ter>
               </Appuis>
               <Appuis>
                    <Num>4</Num>
                    <Im>3731.40898132321081 696.608253479060863</Im>
                    <Ter>-1.01551397855895509 -0.291137533164000595 -7.16319196729328045</Ter>
               </Appuis>
               <Appuis>
                    <Num>5</Num>
                    <Im>3923.57299232482774 2464.1696434020987</Im>
                    <Ter>-0.146514372472133836 -4.2654730141800199 -8.83404790300923359</Ter>
               </Appuis>
               <Appuis>
                    <Num>6</Num>
                    <Im>3054.89353752141051 2683.94169616654153</Im>
                    <Ter>-2.09166268214601381 -2.90088766099825479 -5.24608679582416038</Ter>
               </Appuis>
               <Appuis>
                    <Num>7</Num>
                    <Im>3960.03896713256836 1839.70458984374977</Im>
                    <Ter>0.119734520932343713 -3.17314136204298158 -10.2162965117652309</Ter>
               </Appuis>
               <Appuis>
                    <Num>8</Num>
                    <Im>3934.32673645017667 2988.07608032224061</Im>
                    <Ter>0.676223086369910131 -7.65360590372753968 -11.9340147987619591</Ter>
               </Appuis>
               <Appuis>
                    <Num>9</Num>
                    <Im>4521.19327926619644 3076.7351989744634</Im>
                    <Ter>0.805190995477807814 -4.84338830101087048 -7.21916647584842419</Ter>
               </Appuis>
          </Verif>
          <ConvOri>
               <KnownConv>eConvApero_DistM2C</KnownConv>
          </ConvOri>
     </OrientationConique>
</ExportAPERO>
